odoo/addons/dms_action/README.rst
odoo/addons/dms_action/__init__.py
odoo/addons/dms_action/__manifest__.py
odoo/addons/dms_action/demo/dms_action.xml
odoo/addons/dms_action/i18n/dms_action.pot
odoo/addons/dms_action/i18n/es.po
odoo/addons/dms_action/i18n/it.po
odoo/addons/dms_action/models/__init__.py
odoo/addons/dms_action/models/dms_action.py
odoo/addons/dms_action/models/dms_directory.py
odoo/addons/dms_action/models/dms_file.py
odoo/addons/dms_action/readme/CONFIGURE.rst
odoo/addons/dms_action/readme/CONTRIBUTORS.rst
odoo/addons/dms_action/readme/DESCRIPTION.rst
odoo/addons/dms_action/readme/USAGE.rst
odoo/addons/dms_action/security/ir.model.access.csv
odoo/addons/dms_action/static/description/icon.png
odoo/addons/dms_action/static/description/index.html
odoo/addons/dms_action/static/src/js/dms_action_button_widget.js
odoo/addons/dms_action/static/src/js/dms_action_widget.js
odoo/addons/dms_action/static/src/scss/dms_action_widget.scss
odoo/addons/dms_action/static/src/scss/file_kanban.scss
odoo/addons/dms_action/static/src/xml/dms_action_widget.xml
odoo/addons/dms_action/template/assets.xml
odoo/addons/dms_action/tests/__init__.py
odoo/addons/dms_action/tests/test_action.py
odoo/addons/dms_action/views/dms_action.xml
odoo/addons/dms_action/views/dms_directory.xml
odoo/addons/dms_action/views/dms_file.xml
odoo14_addon_dms_action-14.0.1.0.1.dev10.dist-info/METADATA
odoo14_addon_dms_action-14.0.1.0.1.dev10.dist-info/WHEEL
odoo14_addon_dms_action-14.0.1.0.1.dev10.dist-info/top_level.txt
odoo14_addon_dms_action-14.0.1.0.1.dev10.dist-info/RECORD
